ReutersNews/ReutersNews.py
ReutersNews/__init__.py
ReutersNews-1.0.2.dist-info/LICENSE
ReutersNews-1.0.2.dist-info/METADATA
ReutersNews-1.0.2.dist-info/WHEEL
ReutersNews-1.0.2.dist-info/top_level.txt
ReutersNews-1.0.2.dist-info/RECORD
