Metadata-Version: 2.1
Name: ReutersNews
Version: 1.0.2
Summary: Search company's news on Reuters
Home-page: https://github.com/HurinHu/ReutersNews
Author: Hurin Hu
Author-email: hurin@live.ca
License: UNKNOWN
Platform: UNKNOWN
Classifier: Programming Language :: Python :: 3
Classifier: License :: OSI Approved :: MIT License
Classifier: Operating System :: OS Independent
